sudoku_smt_solvers/__init__.py
sudoku_smt_solvers/benchmarks/__init__.py
sudoku_smt_solvers/benchmarks/benchmark_runner.py
sudoku_smt_solvers/benchmarks/sudoku_generator/__init__.py
sudoku_smt_solvers/benchmarks/sudoku_generator/dfs_solver.py
sudoku_smt_solvers/benchmarks/sudoku_generator/hole_digger.py
sudoku_smt_solvers/benchmarks/sudoku_generator/las_vegas.py
sudoku_smt_solvers/benchmarks/sudoku_generator/sudoku_generator.py
sudoku_smt_solvers/solvers/__init__.py
sudoku_smt_solvers/solvers/cvc5_solver.py
sudoku_smt_solvers/solvers/dpll_solver.py
sudoku_smt_solvers/solvers/dpllt_solver.py
sudoku_smt_solvers/solvers/z3_solver.py
sudoku_smt_solvers/solvers/utils/__init__.py
sudoku_smt_solvers/solvers/utils/sudoku_error.py
sudoku_smt_solvers-1.0.0.dist-info/LICENSE
sudoku_smt_solvers-1.0.0.dist-info/METADATA
sudoku_smt_solvers-1.0.0.dist-info/WHEEL
sudoku_smt_solvers-1.0.0.dist-info/top_level.txt
sudoku_smt_solvers-1.0.0.dist-info/RECORD
