Metadata-Version: 2.2
Name: sudoku_smt_solvers
Version: 1.0.0
Summary: A collection of SAT and SMT solvers for solving Sudoku puzzles
Home-page: https://liamjdavis.github.io/sudoku-smt-solvers
Author: Liam Davis, Tairan 'Ryan' Ji
Author-email: ljdavis27@amherst.edu, tji26@amherst.edu
License: MIT
Classifier: Programming Language :: Python :: 3
Classifier: License :: OSI Approved :: MIT License
Classifier: Operating System :: OS Independent
Requires-Python: >=3.10
License-File: LICENSE
Requires-Dist: cvc5
Requires-Dist: python-sat
Requires-Dist: z3-solver
Dynamic: author
Dynamic: author-email
Dynamic: classifier
Dynamic: description
Dynamic: description-content-type
Dynamic: home-page
Dynamic: license
Dynamic: requires-dist
Dynamic: requires-python
Dynamic: summary
